math_tools_v4_0/.ipynb_checkpoints/__init__-checkpoint.py
math_tools_v4_0/.ipynb_checkpoints/server-checkpoint.py
math_tools_v4_0/__init__.py
math_tools_v4_0/server.py
math_tools_v4_0-0.2.0.dist-info/WHEEL
math_tools_v4_0-0.2.0.dist-info/entry_points.txt
math_tools_v4_0-0.2.0.dist-info/METADATA
math_tools_v4_0-0.2.0.dist-info/RECORD
