Metadata-Version: 2.3
Name: math-tools-v4-0
Version: 0.2.0
Summary: Add your description here
Requires-Dist: fastmcp>=0.1.0
Requires-Dist: mcp>=1.0.0
Requires-Python: >=3.10
